{
  "dist/index.umd.production.js": {
    "bundled": 44413,
    "minified": 13918,
    "gzipped": 4528
  },
  "dist/index.umd.development.js": {
    "bundled": 44537,
    "minified": 13993,
    "gzipped": 4549
  },
  "dist/index.production.js": {
    "bundled": 8379,
    "minified": 5103,
    "gzipped": 1436
  },
  "dist/index.development.js": {
    "bundled": 8379,
    "minified": 5103,
    "gzipped": 1436
  },
  "dist/index.es.js": {
    "bundled": 8058,
    "minified": 4838,
    "gzipped": 1358,
    "treeshaked": {
      "rollup": {
        "code": 270,
        "import_statements": 84
      },
      "webpack": {
        "code": 1347
      }
    }
  }
}
