{
  "dist/index.umd.production.js": {
    "bundled": 30126,
    "minified": 8314,
    "gzipped": 3104
  },
  "dist/index.umd.development.js": {
    "bundled": 30126,
    "minified": 8314,
    "gzipped": 3104
  },
  "dist/index.production.js": {
    "bundled": 7354,
    "minified": 4182,
    "gzipped": 1542
  },
  "dist/index.development.js": {
    "bundled": 7354,
    "minified": 4182,
    "gzipped": 1542
  },
  "dist/index.es.js": {
    "bundled": 7253,
    "minified": 4089,
    "gzipped": 1508,
    "treeshaked": {
      "rollup": {
        "code": 43,
        "import_statements": 43
      },
      "webpack": {
        "code": 1060
      }
    }
  }
}
