{
  "dist/index.umd.production.js": {
    "bundled": 29265,
    "minified": 7394,
    "gzipped": 2876
  },
  "dist/index.umd.development.js": {
    "bundled": 29265,
    "minified": 7394,
    "gzipped": 2876
  },
  "dist/index.production.js": {
    "bundled": 4615,
    "minified": 2584,
    "gzipped": 1143
  },
  "dist/index.development.js": {
    "bundled": 4615,
    "minified": 2584,
    "gzipped": 1143
  },
  "dist/index.es.js": {
    "bundled": 4355,
    "minified": 2373,
    "gzipped": 1070,
    "treeshaked": {
      "rollup": {
        "code": 43,
        "import_statements": 43
      },
      "webpack": {
        "code": 1060
      }
    }
  }
}
